{
    "key": "group_59d64cac01fed",
    "title": "Create User Roles",
    "fields": [
        {
            "key": "field_59d65a29c0f91",
            "label": "Enable Role Creation",
            "name": "roles_enabled",
            "type": "true_false",
            "instructions": "",
            "required": 0,
            "conditional_logic": 0,
            "wrapper": {
                "width": "",
                "class": "",
                "id": ""
            },
            "message": "",
            "default_value": 0,
            "ui": 1,
            "ui_on_text": "",
            "ui_off_text": ""
        },
        {
            "key": "field_59d64cbcd41d5",
            "label": "Add Roles",
            "name": "add_roles",
            "type": "post_object",
            "instructions": "",
            "required": 0,
            "conditional_logic": [
                [
                    {
                        "field": "field_59d65a29c0f91",
                        "operator": "==",
                        "value": "1"
                    }
                ]
            ],
            "wrapper": {
                "width": "",
                "class": "",
                "id": ""
            },
            "post_type": [
                "page"
            ],
            "taxonomy": [],
            "allow_null": 0,
            "multiple": 1,
            "return_format": "object",
            "ui": 1
        }
    ],
    "location": [
        [
            {
                "param": "options_page",
                "operator": "==",
                "value": "theme-general-settings"
            }
        ]
    ],
    "menu_order": 0,
    "position": "normal",
    "style": "default",
    "label_placement": "top",
    "instruction_placement": "label",
    "hide_on_screen": "",
    "active": true,
    "description": "",
    "modified": 1551780845
}